aioprometheus_api_client/__init__.py
aioprometheus_api_client/exceptions.py
aioprometheus_api_client/metric.py
aioprometheus_api_client/metric_range_df.py
aioprometheus_api_client/metric_snapshot_df.py
aioprometheus_api_client/metrics_list.py
aioprometheus_api_client/prometheus_connect.py
aioprometheus_api_client/utils.py
tests/__init__.py
tests/mocked_network.py
tests/test_metric.py
tests/test_metric_range_df.py
tests/test_metric_snapshot_df.py
tests/test_metrics_list.py
tests/test_prometheus_connect.py
tests/test_with_metrics.py
aioprometheus_api_client-0.0.2.dist-info/LICENSE
aioprometheus_api_client-0.0.2.dist-info/METADATA
aioprometheus_api_client-0.0.2.dist-info/WHEEL
aioprometheus_api_client-0.0.2.dist-info/top_level.txt
aioprometheus_api_client-0.0.2.dist-info/RECORD
