Metadata-Version: 2.1
Name: aioprometheus-api-client
Version: 0.0.2
Summary: An async python api to collect data from prometheus
Home-page: https://github.com/trisongz/aioprometheus-api-client
Author: Tri Songz
Author-email: asanmukhani@microsoft.com
Classifier: Programming Language :: Python :: 3.8
Classifier: License :: OSI Approved :: MIT License
Classifier: Operating System :: OS Independent
License-File: LICENSE
Requires-Dist: anyio
Requires-Dist: httpx
Requires-Dist: dateparser
Requires-Dist: pandas (>=1.0.0)
Requires-Dist: numpy
Requires-Dist: matplotlib
Requires-Dist: httmock
